pyDeepP2SA.py
pyDeepP2SA-0.0.8.dist-info/LICENCE.txt
pyDeepP2SA-0.0.8.dist-info/METADATA
pyDeepP2SA-0.0.8.dist-info/WHEEL
pyDeepP2SA-0.0.8.dist-info/top_level.txt
pyDeepP2SA-0.0.8.dist-info/RECORD
